README.md
setup.py
mpyk/__init__.py
mpyk/client.py
mpyk/const.py
mpyk/model.py
mpyk.egg-info/PKG-INFO
mpyk.egg-info/SOURCES.txt
mpyk.egg-info/dependency_links.txt
mpyk.egg-info/requires.txt
mpyk.egg-info/top_level.txt