Metadata-Version: 2.1
Name: mpyk
Version: 0.0.4
Summary: Library for retrieving Wrocław public transportation geolocation data
Home-page: https://github.com/emkor/mpyk
Author: Mateusz Korzeniowski
Author-email: emkor93@gmail.com
License: UNKNOWN
Platform: UNKNOWN
Classifier: Programming Language :: Python :: 3
Classifier: Intended Audience :: Developers
Classifier: License :: OSI Approved :: MIT License
Classifier: Natural Language :: English
Classifier: Operating System :: POSIX :: Linux
Classifier: Operating System :: MacOS
Classifier: Topic :: Utilities
Provides-Extra: dev
